setup.py
src/ProfitDataFrame/ProfitDataFrame.py
src/ProfitDataFrame/__init__.py
src/ProfitDataFrame.egg-info/PKG-INFO
src/ProfitDataFrame.egg-info/SOURCES.txt
src/ProfitDataFrame.egg-info/dependency_links.txt
src/ProfitDataFrame.egg-info/requires.txt
src/ProfitDataFrame.egg-info/top_level.txt