Metadata-Version: 1.0
Name: ProfitDataFrame
Version: 2023.7.19
Summary: This is a package for myself to make data analysis easily, it includes some functions 
